image_processing/__init__.py
image_processing/processing/__init__.py
image_processing/processing/combination.py.py
image_processing/processing/transformation.py.py
image_processing/utils/__init__.py
image_processing/utils/io.py.py
image_processing/utils/plot.py
package_processing-0.0.1.dist-info/METADATA
package_processing-0.0.1.dist-info/WHEEL
package_processing-0.0.1.dist-info/top_level.txt
package_processing-0.0.1.dist-info/RECORD
