Metadata-Version: 2.1
Name: package-processing
Version: 0.0.1
Summary: Image Processing Package using Skimage
Home-page: https://github.com/Will-Moura/image_processing_package.git
Author: William
Author-email: Williammachadomoura@hotmail.com
License: UNKNOWN
Platform: UNKNOWN
Requires-Python: >=3.8
Requires-Dist: matplotlib
Requires-Dist: numpy
Requires-Dist: scikit-image (>=0.16.1)
